generate/__init__.py
generate/exception.py
generate/generate.py
generate/py.typed
generate/utils.py
generate/dist/index.js
generate/dist/index.js.map
generate/method/__init__.py
generate/method/encrypt.py
generate/method/payment.py
generate/node_modules/.package-lock.json
generate/node_modules/.bin/acorn
generate/node_modules/.bin/ts-node
generate/node_modules/.bin/ts-node-cwd
generate/node_modules/.bin/ts-node-esm
generate/node_modules/.bin/ts-node-script
generate/node_modules/.bin/ts-node-transpile-only
generate/node_modules/.bin/ts-script
generate/node_modules/.bin/tsc
generate/node_modules/.bin/tsserver
generate/node_modules/@cspotcode/source-map-support/LICENSE.md
generate/node_modules/@cspotcode/source-map-support/README.md
generate/node_modules/@cspotcode/source-map-support/browser-source-map-support.js
generate/node_modules/@cspotcode/source-map-support/package.json
generate/node_modules/@cspotcode/source-map-support/register-hook-require.d.ts
generate/node_modules/@cspotcode/source-map-support/register-hook-require.js
generate/node_modules/@cspotcode/source-map-support/register.d.ts
generate/node_modules/@cspotcode/source-map-support/register.js
generate/node_modules/@cspotcode/source-map-support/source-map-support.d.ts
generate/node_modules/@cspotcode/source-map-support/source-map-support.js
generate/node_modules/@jridgewell/resolve-uri/LICENSE
generate/node_modules/@jridgewell/resolve-uri/README.md
generate/node_modules/@jridgewell/resolve-uri/package.json
generate/node_modules/@jridgewell/resolve-uri/dist/resolve-uri.mjs
generate/node_modules/@jridgewell/resolve-uri/dist/resolve-uri.mjs.map
generate/node_modules/@jridgewell/resolve-uri/dist/resolve-uri.umd.js
generate/node_modules/@jridgewell/resolve-uri/dist/resolve-uri.umd.js.map
generate/node_modules/@jridgewell/resolve-uri/dist/types/resolve-uri.d.ts
generate/node_modules/@jridgewell/sourcemap-codec/LICENSE
generate/node_modules/@jridgewell/sourcemap-codec/README.md
generate_tools-0.1.7.dist-info/LICENSE
generate_tools-0.1.7.dist-info/METADATA
generate_tools-0.1.7.dist-info/NOTICE
generate_tools-0.1.7.dist-info/WHEEL
generate_tools-0.1.7.dist-info/top_level.txt
generate_tools-0.1.7.dist-info/RECORD
