Metadata-Version: 2.1
Name: generate-tools
Version: 0.1.7
Summary: GenerateTools - Generator of tools for Telegram bots function with Python base.
Home-page: https://github.com/AyiinXd/GenerateTools
Author: AyiinXd
Author-email: ayingaming98@gmail.com
License: GNU Affero General Public License v3.0 (AGPL-3.0)
Project-URL: Bug Tracker, https://github.com/AyiinXd/GenerateTools/issues
Project-URL: Documentation, https://generate_tools.tech
Project-URL: Source Code, https://github.com/AyiinXd/GenerateTools
Platform: UNKNOWN
Classifier: Programming Language :: Python :: 3
Classifier: Programming Language :: Python :: 3.8
Classifier: Programming Language :: Python :: 3.9
Classifier: Programming Language :: Python :: 3.10
Classifier: License :: OSI Approved :: GNU General Public License v3 (GPLv3)
Classifier: Operating System :: OS Independent
Requires-Python: ~=3.7
License-File: LICENSE
License-File: NOTICE
Requires-Dist: pybase64
Requires-Dist: html2text
Requires-Dist: requests
Requires-Dist: pymongo
